{
  "domains": ["torgnybjers.xorcode.org", "torgnybjers.com", "codeberserker.com"],
  "globals": {
    "site_title": "Torgny Bjers",
    "site_url": "http://torgnybjers.com",
    "email": "me@torgnybjers.com",
    "phone": "704-802-2633",
    "disqus": {
      "enabled": true,
      "shortname": "torgny"
    },
    "google_analytics": {
      "enabled": true,
      "account": "UA-9637763-1"
    },
    "social_links": {
      "twitter": "torgnybjers",
      "facebook": "torgny",
      "github": "tbjers",
      "medium": "torgny",
      "stackoverflow": "99481/tbjers",
      "dribbble": false
    },
    "sitemap": {
      "enabled": true,
      "changefreq": "weekly"
    },
    "rollbar": {
      "token": "325e389f1b594c9cac4dabeb68d942d9"
    },
    "cdn": "//d1vdil4xvplvfb.cloudfront.net"
  }
}
